invenio_oarepo_mapping_includes/__init__.py
invenio_oarepo_mapping_includes/config.py
invenio_oarepo_mapping_includes/ext.py
invenio_oarepo_mapping_includes/resolver.py
invenio_oarepo_mapping_includes/version.py
invenio_oarepo_mapping_includes/templates/__init__.py
invenio_oarepo_mapping_includes-1.3.0.dist-info/LICENSE
invenio_oarepo_mapping_includes-1.3.0.dist-info/METADATA
invenio_oarepo_mapping_includes-1.3.0.dist-info/WHEEL
invenio_oarepo_mapping_includes-1.3.0.dist-info/entry_points.txt
invenio_oarepo_mapping_includes-1.3.0.dist-info/top_level.txt
invenio_oarepo_mapping_includes-1.3.0.dist-info/RECORD
